claroai/__init__.py
claroai/api_client.py
claroai/api_response.py
claroai/configuration.py
claroai/exceptions.py
claroai/py.typed
claroai/rest.py
claroai/api/__init__.py
claroai/api/conversation_api.py
claroai/api/interaction_api.py
claroai/api/prediction_api.py
claroai/models/__init__.py
claroai/models/api_success_response.py
claroai/models/author.py
claroai/models/conversation.py
claroai/models/conversation_data.py
claroai/models/conversation_parts.py
claroai/models/conversation_schema.py
claroai/models/conversation_source.py
claroai/models/data_item.py
claroai/models/greeting.py
claroai/models/http_validation_error.py
claroai/models/interaction_data.py
claroai/models/interaction_schema.py
claroai/models/intercom_notification_event_schema.py
claroai/models/item.py
claroai/models/message_schema.py
claroai/models/metadata.py
claroai/models/prediction_type.py
claroai/models/role_enum_schema.py
claroai/models/text_prediction_schema.py
claroai/models/validation_error.py
claroai/models/validation_error_loc_inner.py
claroai/models/webhook_topics.py
claroai-0.0b1.dist-info/METADATA
claroai-0.0b1.dist-info/WHEEL
claroai-0.0b1.dist-info/top_level.txt
claroai-0.0b1.dist-info/RECORD
