Metadata-Version: 2.1
Name: claroai
Version: 0.0b1
Summary: Claro AI Python client
Home-page: https://getclaro.ai
Author: Claro AI
Author-email: hello@getclaro.ai
Keywords: Claro AI,Claro API
Requires-Dist: urllib3 <2.1.0,>=1.25.3
Requires-Dist: python-dateutil
Requires-Dist: pydantic >=2
Requires-Dist: typing-extensions >=4.7.1
